UKLawScraper/CaseHeaderScraper.py
UKLawScraper/CaseInfoScraper.py
UKLawScraper/FullTextScraper.py
UKLawScraper/Save_to_json.py
UKLawScraper/__init__.py
tests/__init__.py
tests/test_module1.py
tests/test_module2.py
tests/test_module3.py
UKLawScraper-0.1.dist-info/LICENSE
UKLawScraper-0.1.dist-info/METADATA
UKLawScraper-0.1.dist-info/WHEEL
UKLawScraper-0.1.dist-info/top_level.txt
UKLawScraper-0.1.dist-info/RECORD
